{
    "schemes": [
        "http"
    ],
    "swagger": "2.0",
    "info": {
        "description": "Starship's flights",
        "title": "SpaceY",
        "contact": {
            "name": "API Support",
            "url": "https://vk.com/bmstu_schedule",
            "email": "bitop@spatecon.ru"
        },
        "license": {
            "name": "AS IS (NO WARRANTY)"
        },
        "version": "1.0"
    },
    "host": "localhost:8080",
    "basePath": "/",
    "paths": {
        "/api/application/admin": {
            "put": {
                "security": [
                    {
                        "ApiKeyAuth": []
                    }
                ],
                "description": "Изменение статуса заявки на принят или отклонен",
                "consumes": [
                    "application/json"
                ],
                "produces": [
                    "application/json"
                ],
                "tags": [
                    "Заявки"
                ],
                "summary": "Меняем статус заявки на принят или отклонен",
                "parameters": [
                    {
                        "description": "Данные для обновления статуса заявки",
                        "name": "request",
                        "in": "body",
                        "required": true,
                        "schema": {
                            "$ref": "#/definitions/ds.AppStatus"
                        }
                    }
                ],
                "responses": {
                    "200": {
                        "description": "OK",
                        "schema": {
                            "type": "string"
                        }
                    },
                    "400": {
                        "description": "Неверный запрос",
                        "schema": {
                            "type": "string"
                        }
                    },
                    "401": {
                        "description": "Неавторизованый пользователь",
                        "schema": {
                            "type": "string"
                        }
                    },
                    "403": {
                        "description": "Нет доступа",
                        "schema": {
                            "type": "string"
                        }
                    },
                    "500": {
                        "description": "Внутренняя ошибка сервера",
                        "schema": {
                            "type": "string"
                        }
                    }
                }
            }
        },
        "/api/application/client": {
            "put": {
                "security": [
                    {
                        "ApiKeyAuth": []
                    }
                ],
                "description": "Изменение статуса заявки на сформирован",
                "consumes": [
                    "application/json"
                ],
                "produces": [
                    "application/json"
                ],
                "tags": [
                    "Заявки"
                ],
                "summary": "Меняем статус заявки на сформирован",
                "parameters": [
                    {
                        "description": "Данные для обновления статуса заявки",
                        "name": "request",
                        "in": "body",
                        "required": true,
                        "schema": {
                            "$ref": "#/definitions/ds.AppStatus"
                        }
                    }
                ],
                "responses": {
                    "200": {
                        "description": "OK",
                        "schema": {
                            "type": "string"
                        }
                    },
                    "400": {
                        "description": "Неверный запрос",
                        "schema": {
                            "type": "string"
                        }
                    },
                    "401": {
                        "description": "Неавторизованый пользователь",
                        "schema": {
                            "type": "string"
                        }
                    },
                    "403": {
                        "description": "Нет доступа",
                        "schema": {
                            "type": "string"
                        }
                    },
                    "500": {
                        "description": "Внутренняя ошибка сервера",
                        "schema": {
                            "type": "string"
                        }
                    }
                }
            }
        },
        "/api/application/{id}": {
            "get": {
                "security": [
                    {
                        "ApiKeyAuth": []
                    }
                ],
                "description": "Получение заявки с услугами",
                "consumes": [
                    "application/json"
                ],
                "produces": [
                    "application/json"
                ],
                "tags": [
                    "Заявки"
                ],
                "summary": "Заявок",
                "parameters": [
                    {
                        "type": "integer",
                        "format": "int64",
                        "default": 1,
                        "description": "ID заявки",
                        "name": "id",
                        "in": "path",
                        "required": true
                    }
                ],
                "responses": {
                    "200": {
                        "description": "OK",
                        "schema": {
                            "type": "string"
                        }
                    },
                    "400": {
                        "description": "Неверный запрос",
                        "schema": {
                            "type": "string"
                        }
                    },
                    "401": {
                        "description": "Неавторизованый пользователь",
                        "schema": {
                            "type": "string"
                        }
                    },
                    "403": {
                        "description": "Нет доступа",
                        "schema": {
                            "type": "string"
                        }
                    },
                    "500": {
                        "description": "Внутренняя ошибка сервера",
                        "schema": {
                            "type": "string"
                        }
                    }
                }
            },
            "delete": {
                "security": [
                    {
                        "ApiKeyAuth": []
                    }
                ],
                "description": "Изменение статуса заявки на удален",
                "consumes": [
                    "application/json"
                ],
                "produces": [
                    "application/json"
                ],
                "tags": [
                    "Заявки"
                ],
                "summary": "Меняем статус заявки на удален",
                "parameters": [
                    {
                        "type": "integer",
                        "format": "int64",
                        "default": 1,
                        "description": "ID заявки",
                        "name": "id",
                        "in": "path",
                        "required": true
                    }
                ],
                "responses": {
                    "200": {
                        "description": "OK",
                        "schema": {
                            "type": "string"
                        }
                    },
                    "400": {
                        "description": "Неверный запрос",
                        "schema": {
                            "type": "string"
                        }
                    },
                    "401": {
                        "description": "Неавторизованый пользователь",
                        "schema": {
                            "type": "string"
                        }
                    },
                    "403": {
                        "description": "Нет доступа",
                        "schema": {
                            "type": "string"
                        }
                    },
                    "500": {
                        "description": "Внутренняя ошибка сервера",
                        "schema": {
                            "type": "string"
                        }
                    }
                }
            }
        },
        "/api/applications": {
            "get": {
                "security": [
                    {
                        "ApiKeyAuth": []
                    }
                ],
                "description": "Получение списка заявок",
                "consumes": [
                    "application/json"
                ],
                "produces": [
                    "application/json"
                ],
                "tags": [
                    "Заявки"
                ],
                "summary": "Список заявок",
                "parameters": [
                    {
                        "type": "string",
                        "description": "Фильтрация по статусу",
                        "name": "status",
                        "in": "query"
                    },
                    {
                        "type": "string",
                        "description": "Фильтрация по дате начала",
                        "name": "date",
                        "in": "query"
                    },
                    {
                        "type": "string",
                        "description": "Фильтрация по дате конца",
                        "name": "date_end",
                        "in": "query"
                    }
                ],
                "responses": {
                    "200": {
                        "description": "OK",
                        "schema": {
                            "type": "string"
                        }
                    },
                    "400": {
                        "description": "Неверный запрос",
                        "schema": {
                            "type": "string"
                        }
                    },
                    "401": {
                        "description": "Неавторизованый пользователь",
                        "schema": {
                            "type": "string"
                        }
                    },
                    "403": {
                        "description": "Нет доступа",
                        "schema": {
                            "type": "string"
                        }
                    },
                    "500": {
                        "description": "Внутренняя ошибка сервера",
                        "schema": {
                            "type": "string"
                        }
                    }
                }
            }
        },
        "/api/login": {
            "post": {
                "description": "Аутентификация пользователя.",
                "consumes": [
                    "application/json"
                ],
                "produces": [
                    "application/json"
                ],
                "tags": [
                    "Пользователи"
                ],
                "summary": "Аутентификация пользователя",
                "parameters": [
                    {
                        "description": "Детали входа",
                        "name": "request",
                        "in": "body",
                        "required": true,
                        "schema": {
                            "$ref": "#/definitions/ds.LoginReq"
                        }
                    }
                ],
                "responses": {
                    "200": {
                        "description": "Успешная аутентификация",
                        "schema": {
                            "$ref": "#/definitions/ds.LoginResp"
                        }
                    },
                    "400": {
                        "description": "Неверный запрос",
                        "schema": {
                            "type": "string"
                        }
                    },
                    "401": {
                        "description": "Неверные учетные данные",
                        "schema": {
                            "type": "string"
                        }
                    },
                    "500": {
                        "description": "Внутренняя ошибка сервера",
                        "schema": {
                            "type": "string"
                        }
                    }
                }
            }
        },
        "/api/logout": {
            "get": {
                "security": [
                    {
                        "ApiKeyAuth": []
                    }
                ],
                "description": "Завершение сеанса текущего пользователя.",
                "consumes": [
                    "application/json"
                ],
                "produces": [
                    "application/json"
                ],
                "tags": [
                    "Пользователи"
                ],
                "summary": "Выход пользователя",
                "responses": {
                    "200": {
                        "description": "Успешный выход",
                        "schema": {
                            "type": "string"
                        }
                    },
                    "400": {
                        "description": "Неверный запрос",
                        "schema": {
                            "type": "string"
                        }
                    },
                    "500": {
                        "description": "Внутренняя ошибка сервера",
                        "schema": {
                            "type": "string"
                        }
                    }
                }
            }
        },
        "/api/ships": {
            "get": {
                "description": "Получение списка кораблей",
                "consumes": [
                    "application/json"
                ],
                "produces": [
                    "application/json"
                ],
                "tags": [
                    "Корабли"
                ],
                "summary": "Список кораблей",
                "parameters": [
                    {
                        "type": "string",
                        "description": "Фильтрация поиска",
                        "name": "search",
                        "in": "query"
                    }
                ],
                "responses": {
                    "200": {
                        "description": "OK",
                        "schema": {
                            "type": "string"
                        }
                    },
                    "400": {
                        "description": "Неверный запрос",
                        "schema": {
                            "type": "string"
                        }
                    },
                    "500": {
                        "description": "Внутренняя ошибка сервера",
                        "schema": {
                            "type": "string"
                        }
                    }
                }
            },
            "put": {
                "security": [
                    {
                        "ApiKeyAuth": []
                    },
                    {
                        "ApiKeyAuth": []
                    }
                ],
                "description": "Изменение информации о корабле",
                "produces": [
                    "application/json"
                ],
                "tags": [
                    "Корабли"
                ],
                "summary": "Изменение информации о корабле",
                "parameters": [
                    {
                        "description": "Обновленная информация о городе",
                        "name": "updated_city",
                        "in": "body",
                        "required": true,
                        "schema": {
                            "$ref": "#/definitions/ds.Ship"
                        }
                    }
                ],
                "responses": {
                    "201": {
                        "description": "Успешное создание космического корабля",
                        "schema": {
                            "$ref": "#/definitions/ds.Ship"
                        }
                    },
                    "400": {
                        "description": "Неверный запрос",
                        "schema": {
                            "type": "string"
                        }
                    },
                    "500": {
                        "description": "Внутренняя ошибка сервера",
                        "schema": {
                            "type": "string"
                        }
                    }
                }
            },
            "post": {
                "security": [
                    {
                        "ApiKeyAuth": []
                    },
                    {
                        "ApiKeyAuth": []
                    }
                ],
                "description": "Создание космического корабля",
                "consumes": [
                    "multipart/form-data"
                ],
                "produces": [
                    "application/json"
                ],
                "tags": [
                    "Корабли"
                ],
                "summary": "Создание корабля",
                "parameters": [
                    {
                        "type": "string",
                        "description": "Название корабля",
                        "name": "Title",
                        "in": "formData",
                        "required": true
                    },
                    {
                        "type": "string",
                        "description": "Описание корабля",
                        "name": "Description",
                        "in": "formData"
                    },
                    {
                        "type": "file",
                        "description": "Изображение корабля",
                        "name": "Image_url",
                        "in": "formData"
                    },
                    {
                        "type": "string",
                        "description": "Ракета-носитель",
                        "name": "Rocket",
                        "in": "formData"
                    },
                    {
                        "type": "string",
                        "description": "Тип корабля",
                        "name": "Type",
                        "in": "formData",
                        "required": true
                    }
                ],
                "responses": {
                    "201": {
                        "description": "Успешное создание космического корабля",
                        "schema": {
                            "$ref": "#/definitions/ds.Ship"
                        }
                    },
                    "400": {
                        "description": "Неверный запрос",
                        "schema": {
                            "type": "string"
                        }
                    },
                    "500": {
                        "description": "Внутренняя ошибка сервера",
                        "schema": {
                            "type": "string"
                        }
                    }
                }
            }
        },
        "/api/ships/application": {
            "post": {
                "security": [
                    {
                        "ApiKeyAuth": []
                    }
                ],
                "description": "Создание или обновление заявки с добавлением услуги",
                "consumes": [
                    "application/json"
                ],
                "produces": [
                    "application/json"
                ],
                "tags": [
                    "Корабли"
                ],
                "summary": "Добавление услуги в заявку или создание новой заявки и добавление в нее услуги",
                "parameters": [
                    {
                        "description": "Данные для добавления города в поход",
                        "name": "request",
                        "in": "body",
                        "required": true,
                        "schema": {
                            "$ref": "#/definitions/ds.ShipToAppReq"
                        }
                    }
                ],
                "responses": {
                    "200": {
                        "description": "Успешное добавление услуги в заявку",
                        "schema": {
                            "type": "string"
                        }
                    },
                    "400": {
                        "description": "Неверный запрос",
                        "schema": {
                            "type": "string"
                        }
                    },
                    "401": {
                        "description": "Ошибка авторизации",
                        "schema": {
                            "type": "string"
                        }
                    },
                    "403": {
                        "description": "Доступ запрещен",
                        "schema": {
                            "type": "string"
                        }
                    }
                }
            }
        },
        "/api/ships/{id}": {
            "get": {
                "description": "Получение информации о корабле по его идентификатору",
                "consumes": [
                    "application/json"
                ],
                "produces": [
                    "application/json"
                ],
                "tags": [
                    "Корабли"
                ],
                "summary": "Получение информации о корабле",
                "parameters": [
                    {
                        "type": "integer",
                        "format": "int64",
                        "default": 1,
                        "description": "ID корабля",
                        "name": "id",
                        "in": "path",
                        "required": true
                    }
                ],
                "responses": {
                    "200": {
                        "description": "Успешный запрос",
                        "schema": {
                            "type": "object",
                            "additionalProperties": true
                        }
                    },
                    "400": {
                        "description": "Неверный запрос",
                        "schema": {
                            "type": "string"
                        }
                    },
                    "500": {
                        "description": "Внутренняя ошибка сервера",
                        "schema": {
                            "type": "string"
                        }
                    }
                }
            }
        },
        "/api/sign_up": {
            "post": {
                "description": "Регистрация нового пользователя.",
                "consumes": [
                    "application/json"
                ],
                "produces": [
                    "application/json"
                ],
                "tags": [
                    "Пользователи"
                ],
                "summary": "Регистрация пользователя",
                "parameters": [
                    {
                        "description": "Детали регистрации",
                        "name": "request",
                        "in": "body",
                        "required": true,
                        "schema": {
                            "$ref": "#/definitions/ds.RegisterReq"
                        }
                    }
                ],
                "responses": {}
            }
        }
    },
    "definitions": {
        "ds.AppStatus": {
            "type": "object",
            "properties": {
                "id": {
                    "type": "integer"
                },
                "status": {
                    "type": "string"
                }
            }
        },
        "ds.LoginReq": {
            "type": "object",
            "properties": {
                "login": {
                    "type": "string"
                },
                "password": {
                    "type": "string"
                }
            }
        },
        "ds.LoginResp": {
            "type": "object",
            "properties": {
                "access_token": {
                    "type": "string"
                },
                "expires_in": {
                    "type": "integer"
                },
                "token_type": {
                    "type": "string"
                }
            }
        },
        "ds.RegisterReq": {
            "type": "object",
            "properties": {
                "name": {
                    "description": "лучше назвать то же самое что login",
                    "type": "string"
                },
                "pass": {
                    "type": "string"
                },
                "phone": {
                    "type": "string"
                },
                "secondName": {
                    "type": "string"
                },
                "userName": {
                    "type": "string"
                }
            }
        },
        "ds.Ship": {
            "type": "object",
            "properties": {
                "description": {
                    "type": "string"
                },
                "id": {
                    "type": "integer"
                },
                "image_url": {
                    "type": "string"
                },
                "is_delete": {
                    "type": "boolean"
                },
                "rocket": {
                    "type": "string"
                },
                "title": {
                    "type": "string"
                },
                "type": {
                    "type": "string"
                }
            }
        },
        "ds.ShipToAppReq": {
            "type": "object",
            "properties": {
                "id_ship": {
                    "type": "integer"
                }
            }
        }
    },
    "securityDefinitions": {
        "ApiKeyAuth": {
            "type": "apiKey",
            "name": "Authorization",
            "in": "header"
        }
    }
}